LICENSE
tui_typer_tutor/__init__.py
tui_typer_tutor/app/__init__.py
tui_typer_tutor/app/ttt.py
tui_typer_tutor/constants/__init__.py
tui_typer_tutor/constants/display_to_textual.py
tui_typer_tutor/core/__init__.py
tui_typer_tutor/core/config.py
tui_typer_tutor/core/metrics.py
tui_typer_tutor/core/scrolled_labels.py
tui_typer_tutor/core/seed_data.py
tui_typer_tutor/core/seed_data.txt
tui_typer_tutor/core/typing.py
tui_typer_tutor/core/uninstall.py
tui_typer_tutor/screens/__init__.py
tui_typer_tutor/screens/help.py
tui_typer_tutor/screens/main.py
tui_typer_tutor/scripts.py
tui_typer_tutor-1.1.2.dist-info/LICENSE
tui_typer_tutor-1.1.2.dist-info/METADATA
tui_typer_tutor-1.1.2.dist-info/WHEEL
tui_typer_tutor-1.1.2.dist-info/entry_points.txt
tui_typer_tutor-1.1.2.dist-info/RECORD
