Metadata-Version: 2.1
Name: tui-typer-tutor
Version: 1.1.2
Summary: Uncomplicated terminal typing practice.
Home-page: https://github.com/kyleking/tui-typer-tutor
License: MIT
Author: Kyle King
Author-email: dev.act.kyle@gmail.com
Requires-Python: >=3.11.2,<4.0.0
Classifier: Development Status :: 1 - Planning
Classifier: License :: OSI Approved :: MIT License
Classifier: Operating System :: OS Independent
Classifier: Programming Language :: Python :: 3
Classifier: Programming Language :: Python :: 3.11
Requires-Dist: arguably (>=1.2.5)
Requires-Dist: bidict (>=0.22.1)
Requires-Dist: corallium (>=0.3.0)
Requires-Dist: platformdirs (>=3.8.0)
Requires-Dist: pydantic (>=2.0.3)
Requires-Dist: pydantic-settings (>=2.0.2)
Requires-Dist: textual (>=0.28.0)
Project-URL: Bug Tracker, https://github.com/kyleking/tui-typer-tutor/issues
Project-URL: Changelog, https://github.com/kyleking/tui-typer-tutor/blob/main/docs/docs/CHANGELOG.md
Project-URL: Documentation, https://tui-typer-tutor.kyleking.me
Project-URL: Repository, https://github.com/kyleking/tui-typer-tutor
